setuptools_scm_about/__about__.py
setuptools_scm_about/__init__.py
setuptools_scm_about-1.0.dist-info/DESCRIPTION.rst
setuptools_scm_about-1.0.dist-info/METADATA
setuptools_scm_about-1.0.dist-info/RECORD
setuptools_scm_about-1.0.dist-info/WHEEL
setuptools_scm_about-1.0.dist-info/entry_points.txt
setuptools_scm_about-1.0.dist-info/metadata.json
setuptools_scm_about-1.0.dist-info/top_level.txt
setuptools_scm_about-1.0.dist-info/zip-safe
