Metadata-Version: 2.0
Name: setuptools-scm-about
Version: 1.0
Summary: setuptools_scm plugin to use version from __about__.py
Home-page: https://github.com/GreatFruitOmsk/setuptools_scm_about
Author: Ilya Kulakov
Author-email: ilya@greatfruit.org
License: MIT
Keywords: setuptools,setuptools_scm,scm,vcs,version
Platform: UNKNOWN
Classifier: Development Status :: 5 - Production/Stable
Classifier: Framework :: Setuptools Plugin
Classifier: Intended Audience :: Developers
Classifier: Topic :: Software Development :: Build Tools
Classifier: License :: OSI Approved :: MIT License
Requires-Dist: setuptools-scm (>=1.10.0)
Provides-Extra: ci
Requires-Dist: pytest; extra == 'ci'
Requires-Dist: codecov; extra == 'ci'
Requires-Dist: docutils; extra == 'ci'
Requires-Dist: flake8; extra == 'ci'
Requires-Dist: pygments; extra == 'ci'
Requires-Dist: pytest-cov; extra == 'ci'
Provides-Extra: tests
Requires-Dist: pytest; extra == 'tests'
